wale/__init__.py
wale/wale.py
wale_sdk-0.1.2.dist-info/METADATA
wale_sdk-0.1.2.dist-info/WHEEL
wale_sdk-0.1.2.dist-info/top_level.txt
wale_sdk-0.1.2.dist-info/RECORD
